{"Event": {"analysis": "2", "date": "2024-05-14", "extends_uuid": "", "info": "smishing_cta_20220408_iocs", "publish_timestamp": "1715718137", "published": true, "threat_level_id": "1", "timestamp": "1715718137", "uuid": "53179059-5781-419e-9d5c-f10bc252dfbb", "Orgc": {"name": "Infoblox", "uuid": "d1c6a726-f132-4ddc-8180-ce3a5b778e65"}, "Tag": [{"colour": "#ffffff", "local": false, "name": "tlp:white", "relationship_type": ""}, {"colour": "#ff00ff", "local": false, "name": "infoblox", "relationship_type": ""}], "Attribute": [{"category": "Network activity", "comment": "", "disable_correlation": false, "first_seen": "2022-04-07T00:00:00+00:00", "timestamp": "1649278800", "to_ids": true, "type": "domain", "uuid": "8a92274b-af2a-45db-941f-42071fa361cf", "value": "smsw1.xyz"}, {"category": "Network activity", "comment": "", "disable_correlation": false, "first_seen": "2022-04-07T00:00:00+00:00", "timestamp": "1649278800", "to_ids": true, "type": "domain", "uuid": "24aaf144-dc17-4bae-b249-769c3e2bcc8d", "value": "mfso1.xyz"}, {"category": "Network activity", "comment": "", "disable_correlation": false, "first_seen": "2022-04-07T00:00:00+00:00", "timestamp": "1649278800", "to_ids": true, "type": "domain", "uuid": "4f7055d4-1d4a-4b4b-a758-282e57c3877c", "value": "pely2.xyz"}, {"category": "Network activity", "comment": "", "disable_correlation": false, "first_seen": "2022-04-07T00:00:00+00:00", "timestamp": "1649278800", "to_ids": true, "type": "domain", "uuid": "cf2db506-9041-4b11-82bb-b553eadf1480", "value": "wtwx2.xyz"}, {"category": "Network activity", "comment": "", "disable_correlation": false, "first_seen": "2022-04-07T00:00:00+00:00", "timestamp": "1649278800", "to_ids": true, "type": "domain", "uuid": "7fc29118-a1e5-401f-9ea6-614c1d7084cf", "value": "khed3.xyz"}, {"category": "Network activity", "comment": "", "disable_correlation": false, "first_seen": "2022-04-07T00:00:00+00:00", "timestamp": "1649278800", "to_ids": true, "type": "domain", "uuid": "8174e831-ab28-493d-bf7b-569b83a8e44b", "value": "mgdi3.xyz"}, {"category": "Network activity", "comment": "", "disable_correlation": false, "first_seen": "2022-04-07T00:00:00+00:00", "timestamp": "1649278800", "to_ids": true, "type": "domain", "uuid": "91316535-5c96-49be-960f-60fa9742db61", "value": "laea4.xyz"}, {"category": "Network activity", "comment": "", "disable_correlation": false, "first_seen": "2022-04-07T00:00:00+00:00", "timestamp": "1649278800", "to_ids": true, "type": "domain", "uuid": "3918916e-76a2-459d-aa82-123ea0a68140", "value": "omyq4.xyz"}, {"category": "Network activity", "comment": "", "disable_correlation": false, "first_seen": "2022-04-07T00:00:00+00:00", "timestamp": "1649278800", "to_ids": true, "type": "domain", "uuid": "5696d282-65df-4965-a623-3fa5e268b230", "value": "qyef5.xyz"}, {"category": "Network activity", "comment": "", "disable_correlation": false, "first_seen": "2022-04-07T00:00:00+00:00", "timestamp": "1649278800", "to_ids": true, "type": "domain", "uuid": "4f4321b4-bc5c-4185-99ce-1baabd502eb7", "value": "idvk5.xyz"}, {"category": "Network activity", "comment": "", "disable_correlation": false, "first_seen": "2022-04-07T00:00:00+00:00", "timestamp": "1649278800", "to_ids": true, "type": "domain", "uuid": "c1c3177b-ce8b-4f71-99ac-728f094cb913", "value": "dqvy6.xyz"}, {"category": "Network activity", "comment": "", "disable_correlation": false, "first_seen": "2022-04-07T00:00:00+00:00", "timestamp": "1649278800", "to_ids": true, "type": "domain", "uuid": "9658b33b-7f66-4a8f-82d6-f79873820d22", "value": "dnmc6.xyz"}, {"category": "Network activity", "comment": "", "disable_correlation": false, "first_seen": "2022-04-07T00:00:00+00:00", "timestamp": "1649278800", "to_ids": true, "type": "domain", "uuid": "f6740a89-c116-4886-b197-ae2eb3c00af2", "value": "igtf7.xyz"}, {"category": "Network activity", "comment": "", "disable_correlation": false, "first_seen": "2022-04-07T00:00:00+00:00", "timestamp": "1649278800", "to_ids": true, "type": "domain", "uuid": "9ae9c48c-9d29-4711-b425-683d9b1df7d5", "value": "kiwv7.xyz"}, {"category": "Network activity", "comment": "", "disable_correlation": false, "first_seen": "2022-04-07T00:00:00+00:00", "timestamp": "1649278800", "to_ids": true, "type": "domain", "uuid": "8cb8f8f1-750c-45be-8846-97232c59cc43", "value": "jjao8.xyz"}, {"category": "Network activity", "comment": "", "disable_correlation": false, "first_seen": "2022-04-07T00:00:00+00:00", "timestamp": "1649278800", "to_ids": true, "type": "domain", "uuid": "f196793e-2d13-495f-afd5-4ec2af3b79c8", "value": "kvde8.xyz"}, {"category": "Network activity", "comment": "", "disable_correlation": false, "first_seen": "2022-04-07T00:00:00+00:00", "timestamp": "1649278800", "to_ids": true, "type": "domain", "uuid": "e0259a31-d0c4-499e-9230-032a7bb2bd4d", "value": "okil9.xyz"}, {"category": "Network activity", "comment": "", "disable_correlation": false, "first_seen": "2022-04-07T00:00:00+00:00", "timestamp": "1649278800", "to_ids": true, "type": "domain", "uuid": "4aa40b56-3d2b-4d26-835a-8f285f7c31ce", "value": "harn9.xyz"}, {"category": "Network activity", "comment": "", "disable_correlation": false, "first_seen": "2022-04-07T00:00:00+00:00", "timestamp": "1649278800", "to_ids": true, "type": "domain", "uuid": "140912ec-1071-4f6b-8931-80cad1704a37", "value": "nill10.xyz"}, {"category": "Network activity", "comment": "", "disable_correlation": false, "first_seen": "2022-04-07T00:00:00+00:00", "timestamp": "1649278800", "to_ids": true, "type": "domain", "uuid": "5db70e96-aea1-4bcc-920e-037fe5f290d5", "value": "ulht10.xyz"}, {"category": "Network activity", "comment": "", "disable_correlation": false, "first_seen": "2022-04-07T00:00:00+00:00", "timestamp": "1649278800", "to_ids": true, "type": "domain", "uuid": "6fba22af-ebb6-4fc3-b847-b3d16232e5fc", "value": "nijf11.xyz"}, {"category": "Network activity", "comment": "", "disable_correlation": false, "first_seen": "2022-04-07T00:00:00+00:00", "timestamp": "1649278800", "to_ids": true, "type": "domain", "uuid": "82a708e9-5741-4ec0-a70a-3d4896a97126", "value": "qgjt11.xyz"}, {"category": "Network activity", "comment": "", "disable_correlation": false, "first_seen": "2022-04-07T00:00:00+00:00", "timestamp": "1649278800", "to_ids": true, "type": "domain", "uuid": "8305f5b4-2edb-4ea7-bd88-8f660dec8f0f", "value": "hcip12.xyz"}, {"category": "Network activity", "comment": "", "disable_correlation": false, "first_seen": "2022-04-07T00:00:00+00:00", "timestamp": "1649278800", "to_ids": true, "type": "domain", "uuid": "88a04284-6b5e-4cfc-a5e8-c303b2e495e5", "value": "jcal12.xyz"}, {"category": "Network activity", "comment": "", "disable_correlation": false, "first_seen": "2022-04-07T00:00:00+00:00", "timestamp": "1649278800", "to_ids": true, "type": "domain", "uuid": "24b2e0a7-4ba2-4e07-878e-b9571951d9f0", "value": "rezb13.xyz"}, {"category": "Network activity", "comment": "", "disable_correlation": false, "first_seen": "2022-04-07T00:00:00+00:00", "timestamp": "1649278800", "to_ids": true, "type": "domain", "uuid": "16cf34c1-250a-4c7d-8bdc-9048247dc714", "value": "tslz13.xyz"}, {"category": "Network activity", "comment": "", "disable_correlation": false, "first_seen": "2022-04-07T00:00:00+00:00", "timestamp": "1649278800", "to_ids": true, "type": "domain", "uuid": "85fccc10-d771-46f0-a447-008cd90fbd67", "value": "hlns14.xyz"}, {"category": "Network activity", "comment": "", "disable_correlation": false, "first_seen": "2022-04-07T00:00:00+00:00", "timestamp": "1649278800", "to_ids": true, "type": "domain", "uuid": "12fcf201-5008-4825-abac-b29d54aa1a82", "value": "izhm14.xyz"}, {"category": "Network activity", "comment": "", "disable_correlation": false, "first_seen": "2022-04-07T00:00:00+00:00", "timestamp": "1649278800", "to_ids": true, "type": "domain", "uuid": "7d72ca4c-aa2e-46c1-b02d-848b8b002a8a", "value": "bgfv15.xyz"}, {"category": "Network activity", "comment": "", "disable_correlation": false, "first_seen": "2022-04-07T00:00:00+00:00", "timestamp": "1649278800", "to_ids": true, "type": "domain", "uuid": "4628f74c-c349-4edd-b28a-f10dc0e729de", "value": "jbeq15.xyz"}, {"category": "Network activity", "comment": "", "disable_correlation": false, "first_seen": "2022-04-07T00:00:00+00:00", "timestamp": "1649278800", "to_ids": true, "type": "domain", "uuid": "87443a56-7601-42b3-a99c-ec18096364af", "value": "mbdq16.xyz"}, {"category": "Network activity", "comment": "", "disable_correlation": false, "first_seen": "2022-04-07T00:00:00+00:00", "timestamp": "1649278800", "to_ids": true, "type": "domain", "uuid": "9d8e9f45-c736-4554-9064-8fd96e8400d7", "value": "acgv16.xyz"}, {"category": "Network activity", "comment": "", "disable_correlation": false, "first_seen": "2022-04-07T00:00:00+00:00", "timestamp": "1649278800", "to_ids": true, "type": "domain", "uuid": "bb482ff4-93fc-468c-960a-e6c3cf8bc1df", "value": "nkeh17.xyz"}, {"category": "Network activity", "comment": "", "disable_correlation": false, "first_seen": "2022-04-07T00:00:00+00:00", "timestamp": "1649278800", "to_ids": true, "type": "domain", "uuid": "c0c2ea12-25c0-4e7a-9b84-ee5a63ee6bbb", "value": "wzae17.xyz"}, {"category": "Network activity", "comment": "", "disable_correlation": false, "first_seen": "2022-04-07T00:00:00+00:00", "timestamp": "1649278800", "to_ids": true, "type": "domain", "uuid": "e9cfe11f-4f11-47bb-91ea-8494af512392", "value": "rtpe18.xyz"}, {"category": "Network activity", "comment": "", "disable_correlation": false, "first_seen": "2022-04-07T00:00:00+00:00", "timestamp": "1649278800", "to_ids": true, "type": "domain", "uuid": "a5d47e2c-4ef0-4861-96d8-579cdac556a5", "value": "yhan18.xyz"}, {"category": "Network activity", "comment": "", "disable_correlation": false, "first_seen": "2022-04-07T00:00:00+00:00", "timestamp": "1649278800", "to_ids": true, "type": "domain", "uuid": "6b4db0d0-6117-43b3-a729-c47b8525ab22", "value": "yamn19.xyz"}, {"category": "Network activity", "comment": "", "disable_correlation": false, "first_seen": "2022-04-07T00:00:00+00:00", "timestamp": "1649278800", "to_ids": true, "type": "domain", "uuid": "9cc06749-7411-4c97-a813-59950469c92d", "value": "sjwf19.xyz"}, {"category": "Network activity", "comment": "", "disable_correlation": false, "first_seen": "2022-04-07T00:00:00+00:00", "timestamp": "1649278800", "to_ids": true, "type": "domain", "uuid": "2096bfe6-c548-4e0d-bd91-0231245892d7", "value": "zdip20.xyz"}, {"category": "Network activity", "comment": "", "disable_correlation": false, "first_seen": "2022-04-07T00:00:00+00:00", "timestamp": "1649278800", "to_ids": true, "type": "domain", "uuid": "0439f141-8626-4635-a1e7-03b3221f9469", "value": "culs20.xyz"}, {"category": "Network activity", "comment": "", "disable_correlation": false, "first_seen": "2022-04-07T00:00:00+00:00", "timestamp": "1649278800", "to_ids": true, "type": "domain", "uuid": "017b7796-29c0-4b60-87fe-b8bb7603a55a", "value": "ezks21.xyz"}, {"category": "Network activity", "comment": "", "disable_correlation": false, "first_seen": "2022-04-07T00:00:00+00:00", "timestamp": "1649278800", "to_ids": true, "type": "domain", "uuid": "20ce504b-9159-4b4f-bd28-7a7733ecd464", "value": "ysfz21.xyz"}, {"category": "Network activity", "comment": "", "disable_correlation": false, "first_seen": "2022-04-07T00:00:00+00:00", "timestamp": "1649278800", "to_ids": true, "type": "domain", "uuid": "c9d3a192-d521-4441-9d67-6b05550ee4a3", "value": "cmrc22.xyz"}, {"category": "Network activity", "comment": "", "disable_correlation": false, "first_seen": "2022-04-07T00:00:00+00:00", "timestamp": "1649278800", "to_ids": true, "type": "domain", "uuid": "6597525b-0ffc-4dba-b9e4-6cc25adb21d0", "value": "vuau22.xyz"}, {"category": "Network activity", "comment": "", "disable_correlation": false, "first_seen": "2022-04-07T00:00:00+00:00", "timestamp": "1649278800", "to_ids": true, "type": "domain", "uuid": "f64921fb-e998-4972-bbc7-f236b5d3c0e6", "value": "jqiz23.xyz"}, {"category": "Network activity", "comment": "", "disable_correlation": false, "first_seen": "2022-04-07T00:00:00+00:00", "timestamp": "1649278800", "to_ids": true, "type": "domain", "uuid": "c8594970-4e36-4ea1-99c0-a0facec62e81", "value": "hadq23.xyz"}, {"category": "Network activity", "comment": "", "disable_correlation": false, "first_seen": "2022-04-07T00:00:00+00:00", "timestamp": "1649278800", "to_ids": true, "type": "domain", "uuid": "0f238d6a-2a5a-4ac9-9746-2832e743d0ff", "value": "ixyv24.xyz"}, {"category": "Network activity", "comment": "", "disable_correlation": false, "first_seen": "2022-04-07T00:00:00+00:00", "timestamp": "1649278800", "to_ids": true, "type": "domain", "uuid": "630f1d8e-4a78-4cf5-9913-b0ecf776b3f5", "value": "lhkp24.xyz"}, {"category": "Network activity", "comment": "", "disable_correlation": false, "first_seen": "2022-04-07T00:00:00+00:00", "timestamp": "1649278800", "to_ids": true, "type": "domain", "uuid": "f2c9cedb-e4f2-4e12-bd2f-7a2ca2dfdfa4", "value": "hpfd25.xyz"}, {"category": "Network activity", "comment": "", "disable_correlation": false, "first_seen": "2022-04-07T00:00:00+00:00", "timestamp": "1649278800", "to_ids": true, "type": "domain", "uuid": "a2b8434a-3d78-4469-b494-ff378c79cdf1", "value": "vjhk25.xyz"}, {"category": "Network activity", "comment": "", "disable_correlation": false, "first_seen": "2022-04-07T00:00:00+00:00", "timestamp": "1649278800", "to_ids": true, "type": "domain", "uuid": "31572cbe-dd9f-406f-9659-09f124e0917b", "value": "uyqb26.xyz"}, {"category": "Network activity", "comment": "", "disable_correlation": false, "first_seen": "2022-04-07T00:00:00+00:00", "timestamp": "1649278800", "to_ids": true, "type": "domain", "uuid": "4402b070-b4f1-4368-84a9-7b26f821a761", "value": "chkn26.xyz"}, {"category": "Network activity", "comment": "", "disable_correlation": false, "first_seen": "2022-04-07T00:00:00+00:00", "timestamp": "1649278800", "to_ids": true, "type": "domain", "uuid": "3eb44a07-61b5-42d2-be15-39c6a0bc60a6", "value": "aust27.xyz"}, {"category": "Network activity", "comment": "", "disable_correlation": false, "first_seen": "2022-04-07T00:00:00+00:00", "timestamp": "1649278800", "to_ids": true, "type": "domain", "uuid": "057d9371-d20e-4085-ae18-45a85967581d", "value": "ltsg27.xyz"}, {"category": "Network activity", "comment": "", "disable_correlation": false, "first_seen": "2022-04-07T00:00:00+00:00", "timestamp": "1649278800", "to_ids": true, "type": "domain", "uuid": "ee843a2b-219e-476c-a2ab-19527471222e", "value": "lcsh28.xyz"}, {"category": "Network activity", "comment": "", "disable_correlation": false, "first_seen": "2022-04-07T00:00:00+00:00", "timestamp": "1649278800", "to_ids": true, "type": "domain", "uuid": "51e66d0f-87b4-4876-a800-288e5078ea78", "value": "aqfo28.xyz"}, {"category": "Network activity", "comment": "", "disable_correlation": false, "first_seen": "2022-04-07T00:00:00+00:00", "timestamp": "1649278800", "to_ids": true, "type": "domain", "uuid": "76d5a142-1737-4633-85c7-e3ea0034958d", "value": "erae29.xyz"}, {"category": "Network activity", "comment": "", "disable_correlation": false, "first_seen": "2022-04-07T00:00:00+00:00", "timestamp": "1649278800", "to_ids": true, "type": "domain", "uuid": "dc96499c-14b4-4957-aa57-41342b7c5b09", "value": "mgjg29.xyz"}, {"category": "Network activity", "comment": "", "disable_correlation": false, "first_seen": "2022-04-07T00:00:00+00:00", "timestamp": "1649278800", "to_ids": true, "type": "domain", "uuid": "7fe01b01-a8a5-4afc-9d16-0c4304eebefe", "value": "ithn30.xyz"}, {"category": "Network activity", "comment": "", "disable_correlation": false, "first_seen": "2022-04-07T00:00:00+00:00", "timestamp": "1649278800", "to_ids": true, "type": "domain", "uuid": "71c7c1dd-8f18-4eae-8e3f-87d6a34efaec", "value": "qinh30.xyz"}, {"category": "Network activity", "comment": "", "disable_correlation": false, "first_seen": "2022-04-07T00:00:00+00:00", "timestamp": "1649278800", "to_ids": true, "type": "domain", "uuid": "6ef67fe7-e69f-4aef-adce-59cd38ae3b44", "value": "mszp31.xyz"}, {"category": "Network activity", "comment": "", "disable_correlation": false, "first_seen": "2022-04-07T00:00:00+00:00", "timestamp": "1649278800", "to_ids": true, "type": "domain", "uuid": "97555a7d-2e25-41ab-a29c-8364173e97b2", "value": "pomz31.xyz"}, {"category": "Network activity", "comment": "", "disable_correlation": false, "first_seen": "2022-04-07T00:00:00+00:00", "timestamp": "1649278800", "to_ids": true, "type": "domain", "uuid": "48c9d860-86d2-4c94-8924-9150b2b327e8", "value": "ciww32.xyz"}, {"category": "Network activity", "comment": "", "disable_correlation": false, "first_seen": "2022-04-07T00:00:00+00:00", "timestamp": "1649278800", "to_ids": true, "type": "domain", "uuid": "16cd1f79-2cf2-4e41-bbee-d937e0422463", "value": "nooa32.xyz"}, {"category": "Network activity", "comment": "", "disable_correlation": false, "first_seen": "2022-04-07T00:00:00+00:00", "timestamp": "1649278800", "to_ids": true, "type": "domain", "uuid": "918abf60-e6d9-48a9-ae22-42c6cd7f5488", "value": "mvfe33.xyz"}, {"category": "Network activity", "comment": "", "disable_correlation": false, "first_seen": "2022-04-07T00:00:00+00:00", "timestamp": "1649278800", "to_ids": true, "type": "domain", "uuid": "ad496447-1da3-457f-9db4-fab0982f48a5", "value": "zmtt33.xyz"}, {"category": "Network activity", "comment": "", "disable_correlation": false, "first_seen": "2022-04-07T00:00:00+00:00", "timestamp": "1649278800", "to_ids": true, "type": "domain", "uuid": "cbb2574d-a1dd-4bb8-9071-2d6beb99bdf6", "value": "jzwc34.xyz"}, {"category": "Network activity", "comment": "", "disable_correlation": false, "first_seen": "2022-04-07T00:00:00+00:00", "timestamp": "1649278800", "to_ids": true, "type": "domain", "uuid": "4efb450a-0dcc-4126-aed3-b22a37e58536", "value": "ktfu34.xyz"}, {"category": "Network activity", "comment": "", "disable_correlation": false, "first_seen": "2022-04-07T00:00:00+00:00", "timestamp": "1649278800", "to_ids": true, "type": "domain", "uuid": "2db28f19-4dc8-4c75-be36-0c3d2d29a1ab", "value": "opdb35.xyz"}, {"category": "Network activity", "comment": "", "disable_correlation": false, "first_seen": "2022-04-07T00:00:00+00:00", "timestamp": "1649278800", "to_ids": true, "type": "domain", "uuid": "c171ceb1-ef1e-430d-bf56-d228b9f91e0e", "value": "rrhn35.xyz"}, {"category": "Network activity", "comment": "", "disable_correlation": false, "first_seen": "2022-04-07T00:00:00+00:00", "timestamp": "1649278800", "to_ids": true, "type": "domain", "uuid": "1d009bbd-4fd9-4397-b4fe-cc471439f324", "value": "gptp36.xyz"}, {"category": "Network activity", "comment": "", "disable_correlation": false, "first_seen": "2022-04-07T00:00:00+00:00", "timestamp": "1649278800", "to_ids": true, "type": "domain", "uuid": "5faf6296-80b3-42a4-8308-22eebc9302c9", "value": "dtus36.xyz"}, {"category": "Network activity", "comment": "", "disable_correlation": false, "first_seen": "2022-04-07T00:00:00+00:00", "timestamp": "1649278800", "to_ids": true, "type": "domain", "uuid": "4e7ca84b-1c0c-4426-8f2f-c5b2426195c1", "value": "qjag37.xyz"}, {"category": "Network activity", "comment": "", "disable_correlation": false, "first_seen": "2022-04-07T00:00:00+00:00", "timestamp": "1649278800", "to_ids": true, "type": "domain", "uuid": "b5d183e5-9265-410d-a1e4-397d8a8ec041", "value": "swbt37.xyz"}, {"category": "Network activity", "comment": "", "disable_correlation": false, "first_seen": "2022-04-07T00:00:00+00:00", "timestamp": "1649278800", "to_ids": true, "type": "domain", "uuid": "1c8f9ebb-cfdb-4bed-b938-4c1f8cb837c5", "value": "upah38.xyz"}, {"category": "Network activity", "comment": "", "disable_correlation": false, "first_seen": "2022-04-07T00:00:00+00:00", "timestamp": "1649278800", "to_ids": true, "type": "domain", "uuid": "1c1afac7-45e6-4fb3-b87a-b979f22a91a8", "value": "ixbc38.xyz"}, {"category": "Network activity", "comment": "", "disable_correlation": false, "first_seen": "2022-04-07T00:00:00+00:00", "timestamp": "1649278800", "to_ids": true, "type": "domain", "uuid": "f2010c05-4653-461f-b5fa-f643db601348", "value": "qfac39.xyz"}, {"category": "Network activity", "comment": "", "disable_correlation": false, "first_seen": "2022-04-07T00:00:00+00:00", "timestamp": "1649278800", "to_ids": true, "type": "domain", "uuid": "3ee27db9-8378-49e3-ace3-b95e1a30b193", "value": "xifj39.xyz"}, {"category": "Network activity", "comment": "", "disable_correlation": false, "first_seen": "2022-04-07T00:00:00+00:00", "timestamp": "1649278800", "to_ids": true, "type": "domain", "uuid": "74498b6f-7066-4914-9a61-cb21579debf7", "value": "aped40.xyz"}, {"category": "Network activity", "comment": "", "disable_correlation": false, "first_seen": "2022-04-07T00:00:00+00:00", "timestamp": "1649278800", "to_ids": true, "type": "domain", "uuid": "dc79dd0a-2a39-40a9-bd09-b7fa28ac5143", "value": "jaig40.xyz"}, {"category": "Network activity", "comment": "", "disable_correlation": false, "first_seen": "2022-04-07T00:00:00+00:00", "timestamp": "1649278800", "to_ids": true, "type": "domain", "uuid": "15263d03-9c8e-4532-9c6f-c552e68fae46", "value": "ckex41.xyz"}, {"category": "Network activity", "comment": "", "disable_correlation": false, "first_seen": "2022-04-07T00:00:00+00:00", "timestamp": "1649278800", "to_ids": true, "type": "domain", "uuid": "e7572a1b-5c52-4ff9-967f-1315f785f2e4", "value": "wgrp41.xyz"}, {"category": "Network activity", "comment": "", "disable_correlation": false, "first_seen": "2022-04-07T00:00:00+00:00", "timestamp": "1649278800", "to_ids": true, "type": "domain", "uuid": "5b22cab6-f5d1-45d1-ba78-71b984344862", "value": "hegz42.xyz"}, {"category": "Network activity", "comment": "", "disable_correlation": false, "first_seen": "2022-04-07T00:00:00+00:00", "timestamp": "1649278800", "to_ids": true, "type": "domain", "uuid": "36adc59c-6fbd-4aac-bbcf-af33f2c097ba", "value": "ciuu42.xyz"}, {"category": "Network activity", "comment": "", "disable_correlation": false, "first_seen": "2022-04-07T00:00:00+00:00", "timestamp": "1649278800", "to_ids": true, "type": "domain", "uuid": "d0cd3bd4-73bc-45e6-90e2-a5b6b1bd428a", "value": "lawn43.xyz"}, {"category": "Network activity", "comment": "", "disable_correlation": false, "first_seen": "2022-04-07T00:00:00+00:00", "timestamp": "1649278800", "to_ids": true, "type": "domain", "uuid": "e9b62f92-c28b-4b38-b816-0d5a9e22bed7", "value": "zoqw43.xyz"}, {"category": "Network activity", "comment": "", "disable_correlation": false, "first_seen": "2022-04-07T00:00:00+00:00", "timestamp": "1649278800", "to_ids": true, "type": "domain", "uuid": "b929d424-341d-4734-bc3e-accfaecbd8da", "value": "zcyj44.xyz"}, {"category": "Network activity", "comment": "", "disable_correlation": false, "first_seen": "2022-04-07T00:00:00+00:00", "timestamp": "1649278800", "to_ids": true, "type": "domain", "uuid": "807b1386-ed95-44f3-84e0-47eada1d35c9", "value": "qbas44.xyz"}, {"category": "Network activity", "comment": "", "disable_correlation": false, "first_seen": "2022-04-07T00:00:00+00:00", "timestamp": "1649278800", "to_ids": true, "type": "domain", "uuid": "1241673c-eeeb-4764-9353-ede59dd81936", "value": "usha45.xyz"}, {"category": "Network activity", "comment": "", "disable_correlation": false, "first_seen": "2022-04-07T00:00:00+00:00", "timestamp": "1649278800", "to_ids": true, "type": "domain", "uuid": "077714b8-65d1-44c8-a8b6-6a11d0ca7156", "value": "zvlg45.xyz"}, {"category": "Network activity", "comment": "", "disable_correlation": false, "first_seen": "2022-04-07T00:00:00+00:00", "timestamp": "1649278800", "to_ids": true, "type": "domain", "uuid": "32eb0257-b882-49e2-8d9b-4ae9e26bbe79", "value": "zlxg46.xyz"}, {"category": "Network activity", "comment": "", "disable_correlation": false, "first_seen": "2022-04-07T00:00:00+00:00", "timestamp": "1649278800", "to_ids": true, "type": "domain", "uuid": "7d973c54-beb3-42d1-8e5d-d49654950737", "value": "qhrq46.xyz"}, {"category": "Network activity", "comment": "", "disable_correlation": false, "first_seen": "2022-04-07T00:00:00+00:00", "timestamp": "1649278800", "to_ids": true, "type": "domain", "uuid": "1446fdcf-9752-4ef5-8b01-b37eb2375561", "value": "fuir47.xyz"}, {"category": "Network activity", "comment": "", "disable_correlation": false, "first_seen": "2022-04-07T00:00:00+00:00", "timestamp": "1649278800", "to_ids": true, "type": "domain", "uuid": "2ea87ad6-2ed7-4dd0-92f4-5d0cc4946e6e", "value": "ixsf47.xyz"}, {"category": "Network activity", "comment": "", "disable_correlation": false, "first_seen": "2022-04-07T00:00:00+00:00", "timestamp": "1649278800", "to_ids": true, "type": "domain", "uuid": "e234d9c1-4c51-4e70-8b09-fb84a42a3375", "value": "vtpf48.xyz"}, {"category": "Network activity", "comment": "", "disable_correlation": false, "first_seen": "2022-04-07T00:00:00+00:00", "timestamp": "1649278800", "to_ids": true, "type": "domain", "uuid": "437e8a27-ad68-422b-8a91-fd3630d6fc92", "value": "ejia48.xyz"}, {"category": "Network activity", "comment": "", "disable_correlation": false, "first_seen": "2022-04-07T00:00:00+00:00", "timestamp": "1649278800", "to_ids": true, "type": "domain", "uuid": "5369b027-7eb7-42b3-8b8a-a9396d99f8e9", "value": "pvut49.xyz"}, {"category": "Network activity", "comment": "", "disable_correlation": false, "first_seen": "2022-04-07T00:00:00+00:00", "timestamp": "1649278800", "to_ids": true, "type": "domain", "uuid": "be7f70ad-c902-480a-aa98-7ca1c546acd5", "value": "sgqz49.xyz"}, {"category": "Network activity", "comment": "", "disable_correlation": false, "first_seen": "2022-04-07T00:00:00+00:00", "timestamp": "1649278800", "to_ids": true, "type": "domain", "uuid": "4709b641-ff75-4a7d-8a7a-10cdf0e5b6c9", "value": "glju50.xyz"}, {"category": "Network activity", "comment": "", "disable_correlation": false, "first_seen": "2022-04-07T00:00:00+00:00", "timestamp": "1649278800", "to_ids": true, "type": "domain", "uuid": "9d54c75d-07fe-4a91-ae3c-2ab4d473a07e", "value": "zmxu50.xyz"}, {"category": "Network activity", "comment": "", "disable_correlation": false, "first_seen": "2022-04-07T00:00:00+00:00", "timestamp": "1649278800", "to_ids": true, "type": "domain", "uuid": "cb4abdbc-de38-4f39-8002-993d4e2f78af", "value": "hggq1.xyz"}, {"category": "Network activity", "comment": "", "disable_correlation": false, "first_seen": "2022-04-07T00:00:00+00:00", "timestamp": "1649278800", "to_ids": true, "type": "domain", "uuid": "5da30ba5-f57c-4d9f-b06d-cda9021a97df", "value": "wkcq2.xyz"}, {"category": "Network activity", "comment": "", "disable_correlation": false, "first_seen": "2022-04-07T00:00:00+00:00", "timestamp": "1649278800", "to_ids": true, "type": "domain", "uuid": "8e62a60d-42f9-43ae-a303-a52b5784450a", "value": "vfar3.xyz"}, {"category": "Network activity", "comment": "", "disable_correlation": false, "first_seen": "2022-04-07T00:00:00+00:00", "timestamp": "1649278800", "to_ids": true, "type": "domain", "uuid": "078118a7-634d-4976-962f-6c1af6f4ffa0", "value": "svgd4.xyz"}, {"category": "Network activity", "comment": "", "disable_correlation": false, "first_seen": "2022-04-07T00:00:00+00:00", "timestamp": "1649278800", "to_ids": true, "type": "domain", "uuid": "fce873b1-d41d-4279-af94-178bac20482b", "value": "fgoy5.xyz"}, {"category": "Network activity", "comment": "", "disable_correlation": false, "first_seen": "2022-04-07T00:00:00+00:00", "timestamp": "1649278800", "to_ids": true, "type": "domain", "uuid": "8672e3d6-e210-487d-8071-4b18c989fe35", "value": "gvhj6.xyz"}, {"category": "Network activity", "comment": "", "disable_correlation": false, "first_seen": "2022-04-07T00:00:00+00:00", "timestamp": "1649278800", "to_ids": true, "type": "domain", "uuid": "ec19b9c6-fa3f-435f-b9d7-d4db0c03f25d", "value": "bepf7.xyz"}, {"category": "Network activity", "comment": "", "disable_correlation": false, "first_seen": "2022-04-07T00:00:00+00:00", "timestamp": "1649278800", "to_ids": true, "type": "domain", "uuid": "ce7dabb9-6853-45be-bb4d-7eaae4a4cdab", "value": "vkri8.xyz"}, {"category": "Network activity", "comment": "", "disable_correlation": false, "first_seen": "2022-04-07T00:00:00+00:00", "timestamp": "1649278800", "to_ids": true, "type": "domain", "uuid": "248fb05c-7f81-4ff3-b093-ea15d7a1efb3", "value": "eknz9.xyz"}, {"category": "Network activity", "comment": "", "disable_correlation": false, "first_seen": "2022-04-07T00:00:00+00:00", "timestamp": "1649278800", "to_ids": true, "type": "domain", "uuid": "c8dd6dc6-3c88-4d13-a6d0-2e5027557bbc", "value": "mslx10.xyz"}, {"category": "Network activity", "comment": "", "disable_correlation": false, "first_seen": "2022-04-07T00:00:00+00:00", "timestamp": "1649278800", "to_ids": true, "type": "domain", "uuid": "4b51ba7a-9297-40b2-b30c-ff2973bbf211", "value": "dfys11.xyz"}, {"category": "Network activity", "comment": "", "disable_correlation": false, "first_seen": "2022-04-07T00:00:00+00:00", "timestamp": "1649278800", "to_ids": true, "type": "domain", "uuid": "07c7eeeb-b11c-4ca7-bf17-c8123b3687c0", "value": "djzy12.xyz"}, {"category": "Network activity", "comment": "", "disable_correlation": false, "first_seen": "2022-04-07T00:00:00+00:00", "timestamp": "1649278800", "to_ids": true, "type": "domain", "uuid": "f8fcc079-860c-4d75-90c9-01df893f99db", "value": "gytr13.xyz"}, {"category": "Network activity", "comment": "", "disable_correlation": false, "first_seen": "2022-04-07T00:00:00+00:00", "timestamp": "1649278800", "to_ids": true, "type": "domain", "uuid": "241de1ea-db5e-4295-aa18-485e6c7937cc", "value": "qhdd14.xyz"}, {"category": "Network activity", "comment": "", "disable_correlation": false, "first_seen": "2022-04-07T00:00:00+00:00", "timestamp": "1649278800", "to_ids": true, "type": "domain", "uuid": "f664001c-434e-4e77-b5de-3a96c3f65a47", "value": "sbqs15.xyz"}, {"category": "Network activity", "comment": "", "disable_correlation": false, "first_seen": "2022-04-07T00:00:00+00:00", "timestamp": "1649278800", "to_ids": true, "type": "domain", "uuid": "46e18202-e520-44fd-aac0-726261c8a72b", "value": "pmlx16.xyz"}, {"category": "Network activity", "comment": "", "disable_correlation": false, "first_seen": "2022-04-07T00:00:00+00:00", "timestamp": "1649278800", "to_ids": true, "type": "domain", "uuid": "61fbdf99-e750-4555-b59e-932230e02ce5", "value": "iphk17.xyz"}, {"category": "Network activity", "comment": "", "disable_correlation": false, "first_seen": "2022-04-07T00:00:00+00:00", "timestamp": "1649278800", "to_ids": true, "type": "domain", "uuid": "7b203683-3ac7-4e87-a642-aafa19631a4d", "value": "opqk18.xyz"}, {"category": "Network activity", "comment": "", "disable_correlation": false, "first_seen": "2022-04-07T00:00:00+00:00", "timestamp": "1649278800", "to_ids": true, "type": "domain", "uuid": "d5562493-9102-476e-b1c0-b5b5d719b0ee", "value": "ntfr19.xyz"}, {"category": "Network activity", "comment": "", "disable_correlation": false, "first_seen": "2022-04-07T00:00:00+00:00", "timestamp": "1649278800", "to_ids": true, "type": "domain", "uuid": "5fb693ff-508b-448b-8e12-aff5e6e6da6b", "value": "cvwm20.xyz"}, {"category": "Network activity", "comment": "", "disable_correlation": false, "first_seen": "2022-04-07T00:00:00+00:00", "timestamp": "1649278800", "to_ids": true, "type": "domain", "uuid": "dc4242cb-76a9-4b5e-aa35-efa79db8de6b", "value": "wtmz1.xyz"}, {"category": "Network activity", "comment": "", "disable_correlation": false, "first_seen": "2022-04-07T00:00:00+00:00", "timestamp": "1649278800", "to_ids": true, "type": "domain", "uuid": "b11f840f-e8b9-4fca-9cc6-fc171c160e38", "value": "xwjv1.xyz"}, {"category": "Network activity", "comment": "", "disable_correlation": false, "first_seen": "2022-04-07T00:00:00+00:00", "timestamp": "1649278800", "to_ids": true, "type": "domain", "uuid": "66852206-a776-484d-be06-eb1e2eb87fe8", "value": "nyxk2.xyz"}, {"category": "Network activity", "comment": "", "disable_correlation": false, "first_seen": "2022-04-07T00:00:00+00:00", "timestamp": "1649278800", "to_ids": true, "type": "domain", "uuid": "67adc708-e203-41d5-842b-2ce331997ac3", "value": "pwnx2.xyz"}, {"category": "Network activity", "comment": "", "disable_correlation": false, "first_seen": "2022-04-07T00:00:00+00:00", "timestamp": "1649278800", "to_ids": true, "type": "domain", "uuid": "ab91fffe-ae21-4fc5-a71f-16a4dfe7f9fd", "value": "dbmy3.xyz"}, {"category": "Network activity", "comment": "", "disable_correlation": false, "first_seen": "2022-04-07T00:00:00+00:00", "timestamp": "1649278800", "to_ids": true, "type": "domain", "uuid": "cf5096ee-272d-43c0-91ca-543998656799", "value": "nvso4.xyz"}, {"category": "Network activity", "comment": "", "disable_correlation": false, "first_seen": "2022-04-07T00:00:00+00:00", "timestamp": "1649278800", "to_ids": true, "type": "domain", "uuid": "f527adbb-7b60-42db-b4d9-ff0586e114c8", "value": "vooy4.xyz"}, {"category": "Network activity", "comment": "", "disable_correlation": false, "first_seen": "2022-03-31T00:00:00+00:00", "timestamp": "1648674000", "to_ids": true, "type": "domain", "uuid": "fc557b4a-d0da-4cb3-8ad1-05f51f9d9937", "value": "hzkr5.xyz"}, {"category": "Network activity", "comment": "", "disable_correlation": false, "first_seen": "2022-04-07T00:00:00+00:00", "timestamp": "1649278800", "to_ids": true, "type": "domain", "uuid": "b22ec6eb-511b-47d6-9744-8f0a39b4ca14", "value": "gddr6.xyz"}, {"category": "Network activity", "comment": "", "disable_correlation": false, "first_seen": "2022-04-07T00:00:00+00:00", "timestamp": "1649278800", "to_ids": true, "type": "domain", "uuid": "aa16a7e9-cb4f-41bc-9cfa-05f8a4db8200", "value": "hhjx7.xyz"}, {"category": "Network activity", "comment": "", "disable_correlation": false, "first_seen": "2022-04-07T00:00:00+00:00", "timestamp": "1649278800", "to_ids": true, "type": "domain", "uuid": "81aa9ecf-d8f1-4b10-994a-db8a23592260", "value": "shcw7.xyz"}, {"category": "Network activity", "comment": "", "disable_correlation": false, "first_seen": "2022-04-07T00:00:00+00:00", "timestamp": "1649278800", "to_ids": true, "type": "domain", "uuid": "51f58f0f-0f64-42b9-9a6c-545219f5648e", "value": "oxwe8.xyz"}, {"category": "Network activity", "comment": "", "disable_correlation": false, "first_seen": "2022-04-07T00:00:00+00:00", "timestamp": "1649278800", "to_ids": true, "type": "domain", "uuid": "6915db49-9d0a-40ef-ba47-2a8f40d80e53", "value": "rpws8.xyz"}, {"category": "Network activity", "comment": "", "disable_correlation": false, "first_seen": "2022-04-07T00:00:00+00:00", "timestamp": "1649278800", "to_ids": true, "type": "domain", "uuid": "0995f5a0-1ec9-434f-a0f6-77512761a8ed", "value": "aqsz9.xyz"}, {"category": "Network activity", "comment": "", "disable_correlation": false, "first_seen": "2022-04-07T00:00:00+00:00", "timestamp": "1649278800", "to_ids": true, "type": "domain", "uuid": "893de394-59df-44b2-8989-1bf56699218f", "value": "ijph9.xyz"}, {"category": "Network activity", "comment": "", "disable_correlation": false, "first_seen": "2022-04-07T00:00:00+00:00", "timestamp": "1649278800", "to_ids": true, "type": "domain", "uuid": "4b2a0b00-68bb-4c28-a463-d06d523bd66b", "value": "sqyc10.xyz"}, {"category": "Network activity", "comment": "", "disable_correlation": false, "first_seen": "2022-04-07T00:00:00+00:00", "timestamp": "1649278800", "to_ids": true, "type": "domain", "uuid": "a4ba4322-36dc-4f2a-8448-6610f22dd0b4", "value": "wszd10.xyz"}, {"category": "Network activity", "comment": "", "disable_correlation": false, "first_seen": "2022-04-07T00:00:00+00:00", "timestamp": "1649278800", "to_ids": true, "type": "domain", "uuid": "90ec3416-280c-449e-82fd-5c91b35d836a", "value": "cegs11.xyz"}, {"category": "Network activity", "comment": "", "disable_correlation": false, "first_seen": "2022-04-07T00:00:00+00:00", "timestamp": "1649278800", "to_ids": true, "type": "domain", "uuid": "a1f5e717-9355-42b8-bb53-918c45bd7d14", "value": "odkp11.xyz"}, {"category": "Network activity", "comment": "", "disable_correlation": false, "first_seen": "2022-04-07T00:00:00+00:00", "timestamp": "1649278800", "to_ids": true, "type": "domain", "uuid": "790df6b0-d8f1-4b5f-9c02-267f61cacb2c", "value": "gshu12.xyz"}, {"category": "Network activity", "comment": "", "disable_correlation": false, "first_seen": "2022-04-07T00:00:00+00:00", "timestamp": "1649278800", "to_ids": true, "type": "domain", "uuid": "98cff6b1-3cf6-4789-8036-eb4f800abb37", "value": "tfll12.xyz"}, {"category": "Network activity", "comment": "", "disable_correlation": false, "first_seen": "2022-04-07T00:00:00+00:00", "timestamp": "1649278800", "to_ids": true, "type": "domain", "uuid": "8c4d4107-5ff8-49b2-b1fc-4a6299a86291", "value": "dysj13.xyz"}, {"category": "Network activity", "comment": "", "disable_correlation": false, "first_seen": "2022-04-07T00:00:00+00:00", "timestamp": "1649278800", "to_ids": true, "type": "domain", "uuid": "36bd6839-5cee-47eb-bd2b-37c22efc7b9e", "value": "tbsb13.xyz"}, {"category": "Network activity", "comment": "", "disable_correlation": false, "first_seen": "2022-04-07T00:00:00+00:00", "timestamp": "1649278800", "to_ids": true, "type": "domain", "uuid": "6714e435-54a6-4179-87b1-c2dd6fc561fa", "value": "ccpt14.xyz"}, {"category": "Network activity", "comment": "", "disable_correlation": false, "first_seen": "2022-04-07T00:00:00+00:00", "timestamp": "1649278800", "to_ids": true, "type": "domain", "uuid": "8b0293d3-f86d-40ac-b737-b854ce853828", "value": "oyfn14.xyz"}, {"category": "Network activity", "comment": "", "disable_correlation": false, "first_seen": "2022-04-07T00:00:00+00:00", "timestamp": "1649278800", "to_ids": true, "type": "domain", "uuid": "fc04347d-2602-48b6-a581-f94d3029be4e", "value": "fgvz15.xyz"}, {"category": "Network activity", "comment": "", "disable_correlation": false, "first_seen": "2022-04-07T00:00:00+00:00", "timestamp": "1649278800", "to_ids": true, "type": "domain", "uuid": "f014c557-4b54-40aa-9350-47118e9374f2", "value": "hquu15.xyz"}, {"category": "Network activity", "comment": "", "disable_correlation": false, "first_seen": "2022-04-07T00:00:00+00:00", "timestamp": "1649278800", "to_ids": true, "type": "domain", "uuid": "0a48c11d-1bc4-4813-b927-ffaa5af50c9b", "value": "jenh16.xyz"}, {"category": "Network activity", "comment": "", "disable_correlation": false, "first_seen": "2022-04-07T00:00:00+00:00", "timestamp": "1649278800", "to_ids": true, "type": "domain", "uuid": "f18085f9-d681-41a5-a833-127b6d93bdc7", "value": "nrfe16.xyz"}, {"category": "Network activity", "comment": "", "disable_correlation": false, "first_seen": "2022-04-07T00:00:00+00:00", "timestamp": "1649278800", "to_ids": true, "type": "domain", "uuid": "1d4d60d5-8026-4156-a960-366e7d31a84b", "value": "fjow17.xyz"}, {"category": "Network activity", "comment": "", "disable_correlation": false, "first_seen": "2022-04-07T00:00:00+00:00", "timestamp": "1649278800", "to_ids": true, "type": "domain", "uuid": "db90d6e7-ee4f-4a85-80b3-6b2f11ae177a", "value": "flgk17.xyz"}, {"category": "Network activity", "comment": "", "disable_correlation": false, "first_seen": "2022-04-07T00:00:00+00:00", "timestamp": "1649278800", "to_ids": true, "type": "domain", "uuid": "d7afa7de-05f3-4d37-85a4-4647cbe3b9cc", "value": "anwa18.xyz"}, {"category": "Network activity", "comment": "", "disable_correlation": false, "first_seen": "2022-04-07T00:00:00+00:00", "timestamp": "1649278800", "to_ids": true, "type": "domain", "uuid": "04da83ef-eafc-421d-9836-9c69526efeab", "value": "dtxp18.xyz"}, {"category": "Network activity", "comment": "", "disable_correlation": false, "first_seen": "2022-04-07T00:00:00+00:00", "timestamp": "1649278800", "to_ids": true, "type": "domain", "uuid": "9e8b94d3-eb8d-4a2d-8e08-5c31b2314188", "value": "inen19.xyz"}, {"category": "Network activity", "comment": "", "disable_correlation": false, "first_seen": "2022-04-07T00:00:00+00:00", "timestamp": "1649278800", "to_ids": true, "type": "domain", "uuid": "8e22b19c-9f7e-4b10-9123-4ac2e98f4e41", "value": "ozhn19.xyz"}, {"category": "Network activity", "comment": "", "disable_correlation": false, "first_seen": "2022-04-07T00:00:00+00:00", "timestamp": "1649278800", "to_ids": true, "type": "domain", "uuid": "f970088b-44c4-475b-a1bf-715a0b2f6be2", "value": "avyc20.xyz"}, {"category": "Network activity", "comment": "", "disable_correlation": false, "first_seen": "2022-03-31T00:00:00+00:00", "timestamp": "1648674000", "to_ids": true, "type": "domain", "uuid": "24180a58-2017-4650-b46c-113d3bbcbb92", "value": "oifc21.xyz"}, {"category": "Network activity", "comment": "", "disable_correlation": false, "first_seen": "2022-04-07T00:00:00+00:00", "timestamp": "1649278800", "to_ids": true, "type": "domain", "uuid": "b66f064f-0687-4483-8cb2-d4d202da6e33", "value": "ukuu21.xyz"}, {"category": "Network activity", "comment": "", "disable_correlation": false, "first_seen": "2022-04-07T00:00:00+00:00", "timestamp": "1649278800", "to_ids": true, "type": "domain", "uuid": "a7f86b49-96a5-40ad-bb14-762da635181c", "value": "dcdh22.xyz"}, {"category": "Network activity", "comment": "", "disable_correlation": false, "first_seen": "2022-04-07T00:00:00+00:00", "timestamp": "1649278800", "to_ids": true, "type": "domain", "uuid": "6ee51a4d-910f-408f-a171-9842ca204c4b", "value": "htur22.xyz"}, {"category": "Network activity", "comment": "", "disable_correlation": false, "first_seen": "2022-04-07T00:00:00+00:00", "timestamp": "1649278800", "to_ids": true, "type": "domain", "uuid": "c8dadfaa-0563-46a4-87f0-8f419f1ecb97", "value": "ohmv23.xyz"}, {"category": "Network activity", "comment": "", "disable_correlation": false, "first_seen": "2022-04-07T00:00:00+00:00", "timestamp": "1649278800", "to_ids": true, "type": "domain", "uuid": "5aed57ad-9926-446b-8485-749df9e1838c", "value": "qflr24.xyz"}, {"category": "Network activity", "comment": "", "disable_correlation": false, "first_seen": "2022-04-07T00:00:00+00:00", "timestamp": "1649278800", "to_ids": true, "type": "domain", "uuid": "54591d82-b7c4-4d9c-907a-1952ba718303", "value": "xnrh24.xyz"}, {"category": "Network activity", "comment": "", "disable_correlation": false, "first_seen": "2022-04-07T00:00:00+00:00", "timestamp": "1649278800", "to_ids": true, "type": "domain", "uuid": "7d3e7563-ee17-4b03-9f6e-8f175088ee37", "value": "snqu25.xyz"}, {"category": "Network activity", "comment": "", "disable_correlation": false, "first_seen": "2022-04-07T00:00:00+00:00", "timestamp": "1649278800", "to_ids": true, "type": "domain", "uuid": "6eb7d7fd-e459-4fa5-bc6f-e3f747f9aac7", "value": "hklk26.xyz"}, {"category": "Network activity", "comment": "", "disable_correlation": false, "first_seen": "2022-04-07T00:00:00+00:00", "timestamp": "1649278800", "to_ids": true, "type": "domain", "uuid": "70a87423-9dd9-4163-8548-514ac42f931f", "value": "vqsr26.xyz"}, {"category": "Network activity", "comment": "", "disable_correlation": false, "first_seen": "2022-04-07T00:00:00+00:00", "timestamp": "1649278800", "to_ids": true, "type": "domain", "uuid": "2b08040a-368a-46af-aa6f-f659525fc6d8", "value": "ahct27.xyz"}, {"category": "Network activity", "comment": "", "disable_correlation": false, "first_seen": "2022-04-07T00:00:00+00:00", "timestamp": "1649278800", "to_ids": true, "type": "domain", "uuid": "9e30ced5-0e69-49ec-aedc-72dfdab5d2a0", "value": "umlp27.xyz"}, {"category": "Network activity", "comment": "", "disable_correlation": false, "first_seen": "2022-04-07T00:00:00+00:00", "timestamp": "1649278800", "to_ids": true, "type": "domain", "uuid": "3ad85180-1d5a-4d12-b28c-b9bafb1c6390", "value": "kdvi28.xyz"}, {"category": "Network activity", "comment": "", "disable_correlation": false, "first_seen": "2022-04-07T00:00:00+00:00", "timestamp": "1649278800", "to_ids": true, "type": "domain", "uuid": "44143e5b-b597-4f4b-8a19-a68dd52df43e", "value": "xuuv28.xyz"}, {"category": "Network activity", "comment": "", "disable_correlation": false, "first_seen": "2022-04-07T00:00:00+00:00", "timestamp": "1649278800", "to_ids": true, "type": "domain", "uuid": "d79b79a5-7ebd-4246-9f61-6012e9d292e9", "value": "lefx29.xyz"}, {"category": "Network activity", "comment": "", "disable_correlation": false, "first_seen": "2022-04-07T00:00:00+00:00", "timestamp": "1649278800", "to_ids": true, "type": "domain", "uuid": "7af57f9e-096f-40d2-860d-e523227f44a9", "value": "atsk30.xyz"}, {"category": "Network activity", "comment": "", "disable_correlation": false, "first_seen": "2022-04-07T00:00:00+00:00", "timestamp": "1649278800", "to_ids": true, "type": "domain", "uuid": "d32c743f-0c9a-4b42-85bf-e043ba9684ad", "value": "vflu31.xyz"}, {"category": "Network activity", "comment": "", "disable_correlation": false, "first_seen": "2022-04-07T00:00:00+00:00", "timestamp": "1649278800", "to_ids": true, "type": "domain", "uuid": "f2193a78-a787-467b-a280-404ad5eb2da5", "value": "zhnv32.xyz"}, {"category": "Network activity", "comment": "", "disable_correlation": false, "first_seen": "2022-04-07T00:00:00+00:00", "timestamp": "1649278800", "to_ids": true, "type": "domain", "uuid": "bed5d24a-a6e1-4977-84a5-aec0f248573b", "value": "xdhh33.xyz"}, {"category": "Network activity", "comment": "", "disable_correlation": false, "first_seen": "2022-04-07T00:00:00+00:00", "timestamp": "1649278800", "to_ids": true, "type": "domain", "uuid": "c7e69d99-954e-4253-bf3f-1fbf5a7572f9", "value": "refp34.xyz"}, {"category": "Network activity", "comment": "", "disable_correlation": false, "first_seen": "2022-04-07T00:00:00+00:00", "timestamp": "1649278800", "to_ids": true, "type": "domain", "uuid": "f8fbfc7f-f89d-44fc-bc56-b084eb071083", "value": "rczt35.xyz"}, {"category": "Network activity", "comment": "", "disable_correlation": false, "first_seen": "2022-04-07T00:00:00+00:00", "timestamp": "1649278800", "to_ids": true, "type": "domain", "uuid": "114cd417-4268-440d-ad9c-f829de0d2292", "value": "gxkk36.xyz"}, {"category": "Network activity", "comment": "", "disable_correlation": false, "first_seen": "2022-04-07T00:00:00+00:00", "timestamp": "1649278800", "to_ids": true, "type": "domain", "uuid": "e1982d47-08e0-47f9-8c60-1e0bc62a6782", "value": "gmec37.xyz"}, {"category": "Network activity", "comment": "", "disable_correlation": false, "first_seen": "2022-04-07T00:00:00+00:00", "timestamp": "1649278800", "to_ids": true, "type": "domain", "uuid": "5f3dfca9-6b48-4459-a211-881086ac2e0d", "value": "ahur38.xyz"}, {"category": "Network activity", "comment": "", "disable_correlation": false, "first_seen": "2022-04-07T00:00:00+00:00", "timestamp": "1649278800", "to_ids": true, "type": "domain", "uuid": "47cda44a-a1bb-4912-821c-7c465bfbe2d7", "value": "asqb39.xyz"}, {"category": "Network activity", "comment": "", "disable_correlation": false, "first_seen": "2022-04-07T00:00:00+00:00", "timestamp": "1649278800", "to_ids": true, "type": "domain", "uuid": "db045753-d26c-43e1-ad92-519fb89eff9c", "value": "bjas40.xyz"}, {"category": "Network activity", "comment": "", "disable_correlation": false, "first_seen": "2022-04-07T00:00:00+00:00", "timestamp": "1649278800", "to_ids": true, "type": "domain", "uuid": "fac2c567-016c-4033-b61e-f4f28c0942d7", "value": "jnmj41.xyz"}, {"category": "Network activity", "comment": "", "disable_correlation": false, "first_seen": "2022-04-07T00:00:00+00:00", "timestamp": "1649278800", "to_ids": true, "type": "domain", "uuid": "2164e844-4d69-4207-80d0-b51100a3a50d", "value": "mfis42.xyz"}, {"category": "Network activity", "comment": "", "disable_correlation": false, "first_seen": "2022-04-07T00:00:00+00:00", "timestamp": "1649278800", "to_ids": true, "type": "domain", "uuid": "91adf64f-f1ad-4532-8da3-6ce91bc77a98", "value": "tyer43.xyz"}, {"category": "Network activity", "comment": "", "disable_correlation": false, "first_seen": "2022-04-07T00:00:00+00:00", "timestamp": "1649278800", "to_ids": true, "type": "domain", "uuid": "d5d64542-812a-4c50-9eaa-2294f31c40c5", "value": "spmu44.xyz"}, {"category": "Network activity", "comment": "", "disable_correlation": false, "first_seen": "2022-04-07T00:00:00+00:00", "timestamp": "1649278800", "to_ids": true, "type": "domain", "uuid": "776b290b-8869-4cb0-b965-99011461b3a6", "value": "bxqi45.xyz"}, {"category": "Network activity", "comment": "", "disable_correlation": false, "first_seen": "2022-04-07T00:00:00+00:00", "timestamp": "1649278800", "to_ids": true, "type": "domain", "uuid": "cc5945f6-b5a8-4512-98c2-07936704656b", "value": "islf46.xyz"}, {"category": "Network activity", "comment": "", "disable_correlation": false, "first_seen": "2022-04-07T00:00:00+00:00", "timestamp": "1649278800", "to_ids": true, "type": "domain", "uuid": "81022565-8a91-40ce-81bf-0f85949fdb3e", "value": "gjdl47.xyz"}, {"category": "Network activity", "comment": "", "disable_correlation": false, "first_seen": "2022-04-07T00:00:00+00:00", "timestamp": "1649278800", "to_ids": true, "type": "domain", "uuid": "b42bc2e5-0394-45bb-a014-5e661cb74848", "value": "ztib48.xyz"}, {"category": "Network activity", "comment": "", "disable_correlation": false, "first_seen": "2022-04-07T00:00:00+00:00", "timestamp": "1649278800", "to_ids": true, "type": "domain", "uuid": "20d9df30-fa60-4800-b873-278973935d51", "value": "ytqk49.xyz"}, {"category": "Network activity", "comment": "", "disable_correlation": false, "first_seen": "2022-04-07T00:00:00+00:00", "timestamp": "1649278800", "to_ids": true, "type": "domain", "uuid": "71d3e7de-0312-4921-988c-35d4ce3f5421", "value": "cepf50.xyz"}, {"category": "Network activity", "comment": "", "disable_correlation": false, "first_seen": "2022-04-07T00:00:00+00:00", "timestamp": "1649278800", "to_ids": true, "type": "domain", "uuid": "2c50bfd0-5ebe-41a0-81c7-804e082439df", "value": "kcap51.xyz"}, {"category": "Network activity", "comment": "", "disable_correlation": false, "first_seen": "2022-04-07T00:00:00+00:00", "timestamp": "1649278800", "to_ids": true, "type": "domain", "uuid": "c6a2115d-fdbf-421f-bd43-4e16f06e1f4c", "value": "dfeo52.xyz"}, {"category": "Network activity", "comment": "", "disable_correlation": false, "first_seen": "2022-04-07T00:00:00+00:00", "timestamp": "1649278800", "to_ids": true, "type": "domain", "uuid": "fceff928-7010-4db0-aed4-f7320f6e884c", "value": "lcrn53.xyz"}, {"category": "Network activity", "comment": "", "disable_correlation": false, "first_seen": "2022-04-07T00:00:00+00:00", "timestamp": "1649278800", "to_ids": true, "type": "domain", "uuid": "d3c96fa6-d8ce-4f5c-90b8-85dadf723b8a", "value": "tgav54.xyz"}, {"category": "Network activity", "comment": "", "disable_correlation": false, "first_seen": "2022-04-07T00:00:00+00:00", "timestamp": "1649278800", "to_ids": true, "type": "domain", "uuid": "24399ead-bca5-4796-aedb-5c1c20f53e95", "value": "sctn56.xyz"}, {"category": "Network activity", "comment": "", "disable_correlation": false, "first_seen": "2022-04-07T00:00:00+00:00", "timestamp": "1649278800", "to_ids": true, "type": "domain", "uuid": "89b78383-4bf0-4549-bb2d-3b4070db4800", "value": "cfzb57.xyz"}, {"category": "Network activity", "comment": "", "disable_correlation": false, "first_seen": "2022-04-07T00:00:00+00:00", "timestamp": "1649278800", "to_ids": true, "type": "domain", "uuid": "343979ff-ae71-448d-b90e-e5389458e33e", "value": "lpdl60.xyz"}, {"category": "Network activity", "comment": "", "disable_correlation": false, "first_seen": "2022-04-07T00:00:00+00:00", "timestamp": "1649278800", "to_ids": true, "type": "domain", "uuid": "c8ee4494-f6d8-4416-b774-a4a0e87d5c30", "value": "bikm61.xyz"}, {"category": "Network activity", "comment": "", "disable_correlation": false, "first_seen": "2022-04-07T00:00:00+00:00", "timestamp": "1649278800", "to_ids": true, "type": "domain", "uuid": "da9a9560-a078-4ec3-a977-a9fe0c8fe2f8", "value": "doif62.xyz"}, {"category": "Network activity", "comment": "", "disable_correlation": false, "first_seen": "2022-04-07T00:00:00+00:00", "timestamp": "1649278800", "to_ids": true, "type": "domain", "uuid": "2942b9be-70d4-435b-8694-074e5651b5ad", "value": "ovel63.xyz"}, {"category": "Network activity", "comment": "", "disable_correlation": false, "first_seen": "2022-04-07T00:00:00+00:00", "timestamp": "1649278800", "to_ids": true, "type": "domain", "uuid": "2436edbf-9314-4adb-a1c7-55809a32ad7d", "value": "bkhr64.xyz"}, {"category": "Network activity", "comment": "", "disable_correlation": false, "first_seen": "2022-04-07T00:00:00+00:00", "timestamp": "1649278800", "to_ids": true, "type": "domain", "uuid": "92060d07-b1c3-40d3-a6cd-0d1ec48aa46a", "value": "vhjp65.xyz"}, {"category": "Network activity", "comment": "", "disable_correlation": false, "first_seen": "2022-04-07T00:00:00+00:00", "timestamp": "1649278800", "to_ids": true, "type": "domain", "uuid": "369b95a4-2caf-4998-a17f-0fc6dd45deaf", "value": "guxv66.xyz"}, {"category": "Network activity", "comment": "", "disable_correlation": false, "first_seen": "2022-04-07T00:00:00+00:00", "timestamp": "1649278800", "to_ids": true, "type": "domain", "uuid": "cbd77a67-0392-4270-92f5-d1d22beaa5ab", "value": "qgud67.xyz"}, {"category": "Network activity", "comment": "", "disable_correlation": false, "first_seen": "2022-04-07T00:00:00+00:00", "timestamp": "1649278800", "to_ids": true, "type": "domain", "uuid": "43a43e3a-4406-49cb-80c3-fbed3a669bc2", "value": "ngkl68.xyz"}, {"category": "Network activity", "comment": "", "disable_correlation": false, "first_seen": "2022-04-07T00:00:00+00:00", "timestamp": "1649278800", "to_ids": true, "type": "domain", "uuid": "4b7b0dc4-028a-435e-b42d-1fb6dfedeb90", "value": "wfug69.xyz"}, {"category": "Network activity", "comment": "", "disable_correlation": false, "first_seen": "2022-04-07T00:00:00+00:00", "timestamp": "1649278800", "to_ids": true, "type": "domain", "uuid": "2b5e7653-e241-493b-9ba8-432d4921961e", "value": "rhlw70.xyz"}, {"category": "Network activity", "comment": "", "disable_correlation": false, "first_seen": "2022-04-07T00:00:00+00:00", "timestamp": "1649278800", "to_ids": true, "type": "domain", "uuid": "58e32d37-c9e5-4b8c-bc89-d3edff0f4f9a", "value": "eaiys1.xyz"}, {"category": "Network activity", "comment": "", "disable_correlation": false, "first_seen": "2022-04-07T00:00:00+00:00", "timestamp": "1649278800", "to_ids": true, "type": "domain", "uuid": "84dc1a46-f0a3-4a6e-adaa-3d720425d36e", "value": "upxut2.xyz"}, {"category": "Network activity", "comment": "", "disable_correlation": false, "first_seen": "2022-04-07T00:00:00+00:00", "timestamp": "1649278800", "to_ids": true, "type": "domain", "uuid": "3df1bd35-304c-47cf-9949-8064c7d85159", "value": "obkom3.xyz"}, {"category": "Network activity", "comment": "", "disable_correlation": false, "first_seen": "2022-04-07T00:00:00+00:00", "timestamp": "1649278800", "to_ids": true, "type": "domain", "uuid": "1197a0ad-bd09-4c56-9158-ee9d5f28a9de", "value": "bsqnt4.xyz"}, {"category": "Network activity", "comment": "", "disable_correlation": false, "first_seen": "2022-04-07T00:00:00+00:00", "timestamp": "1649278800", "to_ids": true, "type": "domain", "uuid": "376c437d-8e62-4ef0-82d8-7211ef63d6c9", "value": "rninf5.xyz"}, {"category": "Network activity", "comment": "", "disable_correlation": false, "first_seen": "2022-04-07T00:00:00+00:00", "timestamp": "1649278800", "to_ids": true, "type": "domain", "uuid": "d5256bd6-ea47-481b-8779-d8c863c698f5", "value": "lrcoq6.xyz"}, {"category": "Network activity", "comment": "", "disable_correlation": false, "first_seen": "2022-04-07T00:00:00+00:00", "timestamp": "1649278800", "to_ids": true, "type": "domain", "uuid": "cb767e35-41e5-4a14-976e-a6926ecc1059", "value": "hacpg7.xyz"}, {"category": "Network activity", "comment": "", "disable_correlation": false, "first_seen": "2022-04-07T00:00:00+00:00", "timestamp": "1649278800", "to_ids": true, "type": "domain", "uuid": "8e1124a8-0c7c-4faf-8db3-ea5540621019", "value": "dfooh8.xyz"}, {"category": "Network activity", "comment": "", "disable_correlation": false, "first_seen": "2022-04-07T00:00:00+00:00", "timestamp": "1649278800", "to_ids": true, "type": "domain", "uuid": "cde4349d-20b3-4b89-a047-8b5de207e211", "value": "slsvv9.xyz"}, {"category": "Network activity", "comment": "", "disable_correlation": false, "first_seen": "2022-04-07T00:00:00+00:00", "timestamp": "1649278800", "to_ids": true, "type": "domain", "uuid": "85a19f35-b1c7-4a38-b489-ff673286a8c1", "value": "eiwku10.xyz"}, {"category": "Network activity", "comment": "", "disable_correlation": false, "first_seen": "2022-04-07T00:00:00+00:00", "timestamp": "1649278800", "to_ids": true, "type": "domain", "uuid": "1e6319ec-8b28-4281-832b-c0ef06a76ce8", "value": "tuafv11.xyz"}, {"category": "Network activity", "comment": "", "disable_correlation": false, "first_seen": "2022-04-07T00:00:00+00:00", "timestamp": "1649278800", "to_ids": true, "type": "domain", "uuid": "1ccecac5-b9ac-4e1d-b5e0-3f0258dab74e", "value": "pvtcb12.xyz"}, {"category": "Network activity", "comment": "", "disable_correlation": false, "first_seen": "2022-04-07T00:00:00+00:00", "timestamp": "1649278800", "to_ids": true, "type": "domain", "uuid": "75fc46b0-a3fc-4623-b1ec-26afa3836962", "value": "aekse13.xyz"}, {"category": "Network activity", "comment": "", "disable_correlation": false, "first_seen": "2022-04-07T00:00:00+00:00", "timestamp": "1649278800", "to_ids": true, "type": "domain", "uuid": "838c1dae-77a6-48a9-a1cb-204abae75b03", "value": "sbbwr14.xyz"}, {"category": "Network activity", "comment": "", "disable_correlation": false, "first_seen": "2022-04-07T00:00:00+00:00", "timestamp": "1649278800", "to_ids": true, "type": "domain", "uuid": "06566876-bce1-4513-9232-c583ea18a63d", "value": "iiddf15.xyz"}, {"category": "Network activity", "comment": "", "disable_correlation": false, "first_seen": "2022-04-07T00:00:00+00:00", "timestamp": "1649278800", "to_ids": true, "type": "domain", "uuid": "6f79c525-84a0-4880-9c8d-a4e8b2a7c75e", "value": "nqldt16.xyz"}, {"category": "Network activity", "comment": "", "disable_correlation": false, "first_seen": "2022-04-07T00:00:00+00:00", "timestamp": "1649278800", "to_ids": true, "type": "domain", "uuid": "298706db-2eb6-4c5a-83ba-4fedba35eea8", "value": "ceewi17.xyz"}, {"category": "Network activity", "comment": "", "disable_correlation": false, "first_seen": "2022-04-07T00:00:00+00:00", "timestamp": "1649278800", "to_ids": true, "type": "domain", "uuid": "d6a11026-c6a9-4bce-b326-ad3668cf5543", "value": "uzzau18.xyz"}, {"category": "Network activity", "comment": "", "disable_correlation": false, "first_seen": "2022-04-07T00:00:00+00:00", "timestamp": "1649278800", "to_ids": true, "type": "domain", "uuid": "3825b1ea-b3c1-4990-a9a2-47b536602c78", "value": "vnaeg19.xyz"}, {"category": "Network activity", "comment": "", "disable_correlation": false, "first_seen": "2022-04-07T00:00:00+00:00", "timestamp": "1649278800", "to_ids": true, "type": "domain", "uuid": "6e807174-8429-431f-9934-af1fc3838592", "value": "bpdmk20.xyz"}, {"category": "Network activity", "comment": "", "disable_correlation": false, "first_seen": "2022-04-07T00:00:00+00:00", "timestamp": "1649278800", "to_ids": true, "type": "domain", "uuid": "ec8fb152-1539-4c4c-834b-98e577ccc9ea", "value": "dyzhu21.xyz"}, {"category": "Network activity", "comment": "", "disable_correlation": false, "first_seen": "2022-04-07T00:00:00+00:00", "timestamp": "1649278800", "to_ids": true, "type": "domain", "uuid": "1ca81e6a-2427-4479-93e3-68380b978efd", "value": "yhqxk22.xyz"}, {"category": "Network activity", "comment": "", "disable_correlation": false, "first_seen": "2022-04-07T00:00:00+00:00", "timestamp": "1649278800", "to_ids": true, "type": "domain", "uuid": "8c2efaa8-1eb6-4868-b71c-262f97d0f3fd", "value": "ebtxe23.xyz"}, {"category": "Network activity", "comment": "", "disable_correlation": false, "first_seen": "2022-04-07T00:00:00+00:00", "timestamp": "1649278800", "to_ids": true, "type": "domain", "uuid": "8335f82e-772e-45f8-9798-faf72a0034a4", "value": "lutod24.xyz"}, {"category": "Network activity", "comment": "", "disable_correlation": false, "first_seen": "2022-04-07T00:00:00+00:00", "timestamp": "1649278800", "to_ids": true, "type": "domain", "uuid": "8971a189-ad71-48fd-8f9b-251f4a6f52f2", "value": "fxzzc25.xyz"}, {"category": "Network activity", "comment": "", "disable_correlation": false, "first_seen": "2022-04-07T00:00:00+00:00", "timestamp": "1649278800", "to_ids": true, "type": "domain", "uuid": "4766e429-2a89-469d-8881-7ccc1e8108cc", "value": "rjebg26.xyz"}, {"category": "Network activity", "comment": "", "disable_correlation": false, "first_seen": "2022-04-07T00:00:00+00:00", "timestamp": "1649278800", "to_ids": true, "type": "domain", "uuid": "f4d806bd-4de7-488c-922b-70a72fb0ad28", "value": "ibjme27.xyz"}, {"category": "Network activity", "comment": "", "disable_correlation": false, "first_seen": "2022-04-07T00:00:00+00:00", "timestamp": "1649278800", "to_ids": true, "type": "domain", "uuid": "930600e6-8059-4b0b-9566-dde397b741de", "value": "svjem28.xyz"}, {"category": "Network activity", "comment": "", "disable_correlation": false, "first_seen": "2022-04-07T00:00:00+00:00", "timestamp": "1649278800", "to_ids": true, "type": "domain", "uuid": "6dff05e6-c57b-4220-b053-b9d76d6ed557", "value": "jbbsg29.xyz"}, {"category": "Network activity", "comment": "", "disable_correlation": false, "first_seen": "2022-04-07T00:00:00+00:00", "timestamp": "1649278800", "to_ids": true, "type": "domain", "uuid": "c88d4a58-6d3c-4080-9ebb-ff179abc6a0f", "value": "qodmu30.xyz"}, {"category": "Network activity", "comment": "", "disable_correlation": false, "first_seen": "2022-04-07T00:00:00+00:00", "timestamp": "1649278800", "to_ids": true, "type": "domain", "uuid": "64b43b74-a6c0-49a0-b5e8-827aa834a82c", "value": "yyaad31.xyz"}, {"category": "Network activity", "comment": "", "disable_correlation": false, "first_seen": "2022-04-07T00:00:00+00:00", "timestamp": "1649278800", "to_ids": true, "type": "domain", "uuid": "1ec25774-6bd7-469a-aae6-6ce552905b88", "value": "plzjc32.xyz"}, {"category": "Network activity", "comment": "", "disable_correlation": false, "first_seen": "2022-03-31T00:00:00+00:00", "timestamp": "1648674000", "to_ids": true, "type": "domain", "uuid": "1f9672cd-1a1a-4a71-8f89-205fa0017be9", "value": "velfu33.xyz"}, {"category": "Network activity", "comment": "", "disable_correlation": false, "first_seen": "2022-04-07T00:00:00+00:00", "timestamp": "1649278800", "to_ids": true, "type": "domain", "uuid": "45b2fa28-24c8-4c92-b976-b03214c446d3", "value": "kxyps34.xyz"}, {"category": "Network activity", "comment": "", "disable_correlation": false, "first_seen": "2022-04-07T00:00:00+00:00", "timestamp": "1649278800", "to_ids": true, "type": "domain", "uuid": "9603d79d-c13e-4ba3-a1fe-ca765873d4d2", "value": "cnwfz35.xyz"}, {"category": "Network activity", "comment": "", "disable_correlation": false, "first_seen": "2022-04-07T00:00:00+00:00", "timestamp": "1649278800", "to_ids": true, "type": "domain", "uuid": "844308ea-741e-47c8-ad0a-07ffb51f820a", "value": "zhgsb36.xyz"}, {"category": "Network activity", "comment": "", "disable_correlation": false, "first_seen": "2022-04-07T00:00:00+00:00", "timestamp": "1649278800", "to_ids": true, "type": "domain", "uuid": "51182816-9669-4ae5-bbb8-4106b0566fe8", "value": "bypmz37.xyz"}, {"category": "Network activity", "comment": "", "disable_correlation": false, "first_seen": "2022-04-07T00:00:00+00:00", "timestamp": "1649278800", "to_ids": true, "type": "domain", "uuid": "9072d4bb-f6a8-4ead-b046-09d1ef6f4159", "value": "xnqno38.xyz"}, {"category": "Network activity", "comment": "", "disable_correlation": false, "first_seen": "2022-04-07T00:00:00+00:00", "timestamp": "1649278800", "to_ids": true, "type": "domain", "uuid": "dd93b0d1-14bc-4d8d-b4b3-9230a7d46022", "value": "ccpxd39.xyz"}, {"category": "Network activity", "comment": "", "disable_correlation": false, "first_seen": "2022-04-07T00:00:00+00:00", "timestamp": "1649278800", "to_ids": true, "type": "domain", "uuid": "7d5beec2-5e89-4794-b45b-a74fbe02e586", "value": "qsbhi40.xyz"}, {"category": "Network activity", "comment": "", "disable_correlation": false, "first_seen": "2022-04-07T00:00:00+00:00", "timestamp": "1649278800", "to_ids": true, "type": "domain", "uuid": "2a4f68f8-3714-45e5-ada0-2f00f62fe6ea", "value": "qhacw41.xyz"}, {"category": "Network activity", "comment": "", "disable_correlation": false, "first_seen": "2022-04-07T00:00:00+00:00", "timestamp": "1649278800", "to_ids": true, "type": "domain", "uuid": "a70012a1-4ab3-45e6-82a5-68a48d79be19", "value": "iwbxe42.xyz"}, {"category": "Network activity", "comment": "", "disable_correlation": false, "first_seen": "2022-04-07T00:00:00+00:00", "timestamp": "1649278800", "to_ids": true, "type": "domain", "uuid": "3d0becb6-1ad0-4338-b3ae-fd46e782e040", "value": "snqwr43.xyz"}, {"category": "Network activity", "comment": "", "disable_correlation": false, "first_seen": "2022-04-07T00:00:00+00:00", "timestamp": "1649278800", "to_ids": true, "type": "domain", "uuid": "0c03d3b5-295f-46b4-9302-8f25e70ae1ed", "value": "gxrgf44.xyz"}, {"category": "Network activity", "comment": "", "disable_correlation": false, "first_seen": "2022-04-07T00:00:00+00:00", "timestamp": "1649278800", "to_ids": true, "type": "domain", "uuid": "9f50e06a-fd3b-4e3b-84be-3abb60dc76be", "value": "jfbku45.xyz"}, {"category": "Network activity", "comment": "", "disable_correlation": false, "first_seen": "2022-03-31T00:00:00+00:00", "timestamp": "1648674000", "to_ids": true, "type": "domain", "uuid": "264da322-7d82-46dd-9a7c-04b70f68da5d", "value": "einsj46.xyz"}, {"category": "Network activity", "comment": "", "disable_correlation": false, "first_seen": "2022-04-07T00:00:00+00:00", "timestamp": "1649278800", "to_ids": true, "type": "domain", "uuid": "9c6b571a-056e-4386-81fb-95077edca2aa", "value": "sirdt47.xyz"}, {"category": "Network activity", "comment": "", "disable_correlation": false, "first_seen": "2022-03-31T00:00:00+00:00", "timestamp": "1648674000", "to_ids": true, "type": "domain", "uuid": "a68bdf65-f843-4a78-b934-cd24c973b58e", "value": "gcfed48.xyz"}, {"category": "Network activity", "comment": "", "disable_correlation": false, "first_seen": "2022-04-07T00:00:00+00:00", "timestamp": "1649278800", "to_ids": true, "type": "domain", "uuid": "3722ba90-44ab-45e9-bee9-516f75d2f299", "value": "hnxxd49.xyz"}, {"category": "Network activity", "comment": "", "disable_correlation": false, "first_seen": "2022-04-07T00:00:00+00:00", "timestamp": "1649278800", "to_ids": true, "type": "domain", "uuid": "dba0d178-70f0-43e2-9f37-69d6fda75919", "value": "jpjhz50.xyz"}, {"category": "Network activity", "comment": "", "disable_correlation": false, "first_seen": "2022-04-07T00:00:00+00:00", "timestamp": "1649278800", "to_ids": true, "type": "domain", "uuid": "70e68548-1857-4c6e-8e3b-bc8e7cf28413", "value": "pycrm2.xyz"}, {"category": "Network activity", "comment": "", "disable_correlation": false, "first_seen": "2022-03-31T00:00:00+00:00", "timestamp": "1648674000", "to_ids": true, "type": "domain", "uuid": "0b3a6c53-811a-45c6-a27f-c6a3933f73fe", "value": "easyechoes.com"}, {"category": "Network activity", "comment": "", "disable_correlation": false, "first_seen": "2022-03-31T00:00:00+00:00", "timestamp": "1648674000", "to_ids": true, "type": "domain", "uuid": "a50ba20e-1366-4b72-929e-2b305e601a8b", "value": "flagshipsteak.com"}, {"category": "Network activity", "comment": "", "disable_correlation": false, "first_seen": "2022-03-31T00:00:00+00:00", "timestamp": "1648674000", "to_ids": true, "type": "domain", "uuid": "ea7fc61a-bb75-4b8d-a93a-50ed868a5d7f", "value": "glittersisgold.com"}, {"category": "Network activity", "comment": "", "disable_correlation": false, "first_seen": "2022-03-31T00:00:00+00:00", "timestamp": "1648674000", "to_ids": true, "type": "domain", "uuid": "17f6b49c-c10a-497b-861c-e070a6c641fc", "value": "goodasgold.shop"}, {"category": "Network activity", "comment": "", "disable_correlation": false, "first_seen": "2022-03-31T00:00:00+00:00", "timestamp": "1648674000", "to_ids": true, "type": "domain", "uuid": "e9eb56b8-6333-4408-88ed-04e68bf5af08", "value": "takeoneforlove.com"}, {"category": "Network activity", "comment": "", "disable_correlation": false, "first_seen": "2022-03-31T00:00:00+00:00", "timestamp": "1648674000", "to_ids": true, "type": "domain", "uuid": "367bff57-b047-4401-b59e-f80290ce2619", "value": "u30487.xyz"}, {"category": "Network activity", "comment": "", "disable_correlation": false, "first_seen": "2022-03-31T00:00:00+00:00", "timestamp": "1648674000", "to_ids": true, "type": "domain", "uuid": "7f331048-eab6-48b2-93f1-576ce039f27c", "value": "eshatl.xyz"}, {"category": "Network activity", "comment": "", "disable_correlation": false, "first_seen": "2022-03-31T00:00:00+00:00", "timestamp": "1648674000", "to_ids": true, "type": "domain", "uuid": "9702325e-1915-4e0f-ae7a-9540f56f4623", "value": "smartfashiondaily.com"}]}}